jupyterlab_ensure_clone/__init__.py
jupyterlab_ensure_clone/_version.py
jupyterlab_ensure_clone/handlers.py
jupyterlab_ensure_clone/tests/__init__.py
jupyterlab_ensure_clone/tests/test_handlers.py
jupyterlab_ensure_clone-0.1.9.data/data/etc/jupyter/jupyter_server_config.d/jupyterlab_ensure_clone.json
jupyterlab_ensure_clone-0.1.9.data/data/share/jupyter/labextensions/jupyterlab-ensure-clone/package.json
jupyterlab_ensure_clone-0.1.9.data/data/share/jupyter/labextensions/jupyterlab-ensure-clone/schemas/jupyterlab-ensure-clone/package.json.orig
jupyterlab_ensure_clone-0.1.9.data/data/share/jupyter/labextensions/jupyterlab-ensure-clone/schemas/jupyterlab-ensure-clone/plugin.json
jupyterlab_ensure_clone-0.1.9.data/data/share/jupyter/labextensions/jupyterlab-ensure-clone/static/675.c95703737bf4d1b23648.js
jupyterlab_ensure_clone-0.1.9.data/data/share/jupyter/labextensions/jupyterlab-ensure-clone/static/728.91555db764042bc4d734.js
jupyterlab_ensure_clone-0.1.9.data/data/share/jupyter/labextensions/jupyterlab-ensure-clone/static/remoteEntry.b435a0960c703b3365c7.js
jupyterlab_ensure_clone-0.1.9.data/data/share/jupyter/labextensions/jupyterlab-ensure-clone/static/style.js
jupyterlab_ensure_clone-0.1.9.data/data/share/jupyter/labextensions/jupyterlab-ensure-clone/static/third-party-licenses.json
jupyterlab_ensure_clone-0.1.9.data/data/share/jupyter/labextensions/jupyterlab-ensure-clone/install.json
jupyterlab_ensure_clone-0.1.9.dist-info/METADATA
jupyterlab_ensure_clone-0.1.9.dist-info/WHEEL
jupyterlab_ensure_clone-0.1.9.dist-info/licenses/LICENSE
jupyterlab_ensure_clone-0.1.9.dist-info/RECORD
