Metadata-Version: 2.4
Name: jupyterlab_ensure_clone
Version: 0.1.9
Summary: Ensure a git repo has been cloned at startup.
Project-URL: Homepage, https://github.com/chicagotrading/jupyterlab-ensure-clone
Project-URL: Bug Tracker, https://github.com/chicagotrading/jupyterlab-ensure-clone/issues
Project-URL: Repository, https://github.com/chicagotrading/jupyterlab-ensure-clone.git
Author-email: Joshua Bronson <joshua.bronson@chicagotrading.com>
License: BSD 3-Clause License
License-File: LICENSE
Keywords: jupyter,jupyterlab,jupyterlab-extension
Classifier: Framework :: Jupyter
Classifier: Framework :: Jupyter :: JupyterLab
Classifier: Framework :: Jupyter :: JupyterLab :: 4
Classifier: Framework :: Jupyter :: JupyterLab :: Extensions
Classifier: Framework :: Jupyter :: JupyterLab :: Extensions :: Prebuilt
Classifier: License :: OSI Approved :: BSD License
Classifier: Programming Language :: Python
Classifier: Programming Language :: Python :: 3
Classifier: Programming Language :: Python :: 3.9
Classifier: Programming Language :: Python :: 3.10
Classifier: Programming Language :: Python :: 3.11
Classifier: Programming Language :: Python :: 3.12
Classifier: Programming Language :: Python :: 3.13
Requires-Python: >=3.9
Requires-Dist: jupyter-server<3,>=2.4.0
Provides-Extra: test
Requires-Dist: coverage; extra == 'test'
Requires-Dist: pytest; extra == 'test'
Requires-Dist: pytest-asyncio; extra == 'test'
Requires-Dist: pytest-cov; extra == 'test'
Requires-Dist: pytest-jupyter[server]>=0.6.0; extra == 'test'
